MANIFEST.in
setup.py
pysplice/__init__.py
pysplice/_splice.c
pysplice/cffi_build.py
pysplice.egg-info/PKG-INFO
pysplice.egg-info/SOURCES.txt
pysplice.egg-info/dependency_links.txt
pysplice.egg-info/not-zip-safe
pysplice.egg-info/requires.txt
pysplice.egg-info/top_level.txt
pysplice/__pycache__/__init__.cpython-34.pyc
pysplice/__pycache__/__init__.cpython-35.pyc
pysplice/__pycache__/__init__.pypy3-23.pyc
pysplice/__pycache__/__init__.pypy3-24.pyc
test/test_splice.py