Metadata-Version: 1.1
Name: pysplice
Version: 0.1.0
Summary: CFFI wrapper around the splice syscall
Home-page: https://github.com/berdario/pysplice
Author: Dario Bertini
Author-email: berdario+pypi@gmail.com
License: MIT License
Platform: UNKNOWN
Classifier: Programming Language :: Python :: 3
Classifier: Intended Audience :: Developers
Classifier: Operating System :: POSIX :: Linux
